{
    "client_email":"ezequielmarcel2@gmail.com",
    "token_uri":"https://oauth2.googleapis.com/token",
    "web":{
        "client_id":"406469731073-2400mqjrn0232cta7l72122nal44m9bn.apps.googleusercontent.com",
        "project_id":"idyllic-striker-423412-c8",
        "auth_uri":"https://accounts.google.com/o/oauth2/auth",
        "token_uri":"https://oauth2.googleapis.com/token",
        "auth_provider_x509_cert_url":"https://www.googleapis.com/oauth2/v1/certs",
        "client_secret":"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",
        "redirect_uris":[
            "http://localhost:8000/auth/google",
            "http://localhost:8280/auth/google",
            "https://api.gstock.francelsoft.com/user/auth/google",
            "https://apidev.gstock.francelsoft.com/user/auth/google",
            "http://apidev.gstock.francelsoft.com/user/auth/google",
            "http://api.gstock.francelsoft.com/user/auth/google"],
        "javascript_origins":[
            "http://localhost:8000",
            "https://api.gstock.francelsoft.com",
            "https://apidev.gstock.francelsoft.com"
        ]
    }
}